procgen/state_test.py
procgen/interactive.py
procgen/env_test.py
procgen/gym_registration.py
procgen/__init__.py
procgen/builder.py
procgen/env.py
procgen/version.txt
procgen/examples/random_agent_gym.py
procgen/examples/random_agent_gym3.py
procgen/examples/__init__.py
procgen/data/prebuilt/libenv.so
procgen/data/assets/platform_backgrounds/landscape1.png
procgen/data/assets/platform_backgrounds/alien_bg.png
procgen/data/assets/platform_backgrounds/battleback7.png
procgen/data/assets/platform_backgrounds/colored_desert.png
procgen/data/assets/platform_backgrounds/airadventurelevel1.png
procgen/data/assets/platform_backgrounds/battleback6.png
procgen/data/assets/platform_backgrounds/airadventurelevel4.png
procgen/data/assets/platform_backgrounds/battleback9.png
procgen/data/assets/platform_backgrounds/battleback1.png
procgen/data/assets/platform_backgrounds/sunrise.png
procgen/data/assets/platform_backgrounds/battleback4.png
procgen/data/assets/platform_backgrounds/battleback3.png
procgen/data/assets/platform_backgrounds/scifi_bg.png
procgen/data/assets/platform_backgrounds/airadventurelevel2.png
procgen/data/assets/platform_backgrounds/airadventurelevel3.png
procgen/data/assets/platform_backgrounds/living_tissue_bg.png
procgen/data/assets/platform_backgrounds/battleback5.png
procgen/data/assets/platform_backgrounds/cyberpunk_bg.png
procgen/data/assets/platform_backgrounds/another_world_bg.png
procgen/data/assets/platform_backgrounds/caverns.png
procgen/data/assets/platform_backgrounds/landscape2.png
procgen/data/assets/platform_backgrounds/battleback2.png
procgen/data/assets/platform_backgrounds/colored_grass.png
procgen/data/assets/platform_backgrounds/battleback10.png
procgen/data/assets/platform_backgrounds/colored_shroom.png
procgen/data/assets/platform_backgrounds/battleback8.png
procgen/data/assets/platform_backgrounds/landscape3.png
procgen/data/assets/platform_backgrounds/parallax_forest.png
procgen-0.10.7.dist-info/RECORD
procgen-0.10.7.dist-info/top_level.txt
procgen-0.10.7.dist-info/LICENSE
procgen-0.10.7.dist-info/WHEEL
procgen-0.10.7.dist-info/METADATA
